opentelemetry/exception/ext/__init__.py
opentelemetry/exception/ext/_internal/exception_recorder.py
opentelemetry_exception_ext-0.0.4.dist-info/METADATA
opentelemetry_exception_ext-0.0.4.dist-info/WHEEL
opentelemetry_exception_ext-0.0.4.dist-info/licenses/LICENSE
opentelemetry_exception_ext-0.0.4.dist-info/RECORD
