Metadata-Version: 2.1
Name: opentelemetry-exception-ext
Version: 0.0.4
Summary: OpenTelemetry extension for exception
Project-URL: Homepage, https://github.com/vaxila-labs/python-opentelemetry-exception-ext
Project-URL: Bug Tracker, https://github.com/vaxila-labs/python-opentelemetry-exception-ext/issues
Author-email: Vaxila Labs <hello@vaxila-labs.com>
License-File: LICENSE
Classifier: License :: OSI Approved :: MIT License
Classifier: Operating System :: OS Independent
Classifier: Programming Language :: Python :: 3
Requires-Python: >=3.7
Requires-Dist: opentelemetry-sdk~=1.12
